prometheus/__init__.py
prometheus/admin/__init__.py
prometheus/admin/actions.py
prometheus/admin/admin.py
prometheus/admin/filters.py
prometheus/admin/multiupload.py
prometheus/conf/__init__.py
prometheus/conf/default_settings.py
prometheus/db/__init__.py
prometheus/db/abstract.py
prometheus/db/enumerates.py
prometheus/db/image.py
prometheus/http/__init__.py
prometheus/http/response.py
prometheus/middlewares/__init__.py
prometheus/middlewares/language.py
prometheus/template_backends/__init__.py
prometheus/template_backends/jinja2/__init__.py
prometheus/template_backends/jinja2/globals/__init__.py
prometheus/template_backends/jinja2/globals/datetime.py
prometheus/template_backends/jinja2/globals/i18n.py
prometheus/template_backends/jinja2/globals/images.py
prometheus/template_backends/jinja2/globals/numbers.py
prometheus/template_backends/jinja2/globals/settings.py
prometheus/template_backends/jinja2/globals/static.py
prometheus/template_backends/jinja2/globals/text.py
prometheus/template_backends/jinja2/globals/extensions/__init__.py
prometheus/template_backends/jinja2/globals/extensions/cache.py
prometheus/template_backends/jinja2/globals/extensions/spaceless.py
prometheus/utils/__init__.py
prometheus/utils/array.py
prometheus/utils/datetime.py
prometheus/utils/dicts.py
prometheus/utils/email.py
prometheus/utils/i18n.py
prometheus/utils/modeltranslation.py
prometheus/utils/passwords.py
prometheus/utils/thumbnail_processors.py
prometheus_framework-0.1.3.dist-info/LICENSE.txt
prometheus_framework-0.1.3.dist-info/METADATA
prometheus_framework-0.1.3.dist-info/RECORD
prometheus_framework-0.1.3.dist-info/WHEEL
prometheus_framework-0.1.3.dist-info/top_level.txt
