Metadata-Version: 2.1
Name: prometheus-framework
Version: 0.1.3
Summary: Prometheus Content management system
Home-page: https://github.com/face-digital/prometheus_framework
Author: FACE Digital
Author-email: wizzzet@gmail.com
License: UNKNOWN
Project-URL: Bug Reports, https://github.com/face-digital/prometheus_framework/issues
Project-URL: Source, https://github.com/face-digital/prometheus_framework
Keywords: Framework based on Django Rest Framework
Platform: UNKNOWN
Classifier: Development Status :: 3 - Alpha
Classifier: Intended Audience :: Developers
Classifier: Topic :: Software Development :: Build Tools
Classifier: License :: OSI Approved :: MIT License
Classifier: Programming Language :: Python :: 3
Classifier: Programming Language :: Python :: 3.4
Classifier: Programming Language :: Python :: 3.5
Classifier: Programming Language :: Python :: 3.6
Provides-Extra: test
Provides-Extra: dev
Provides-Extra: dev
Requires-Dist: check-manifest; extra == 'dev'
Provides-Extra: test
Requires-Dist: coverage; extra == 'test'
